{
	"configurations" : 
	[
		{
			"directories" : 
			[
				{
					"build" : ".",
					"jsonFile" : "directory-.-Debug-f5ebdc15457944623624.json",
					"minimumCMakeVersion" : 
					{
						"string" : "3.27"
					},
					"projectIndex" : 0,
					"source" : ".",
					"targetIndexes" : 
					[
						0
					]
				}
			],
			"name" : "Debug",
			"projects" : 
			[
				{
					"directoryIndexes" : 
					[
						0
					],
					"name" : "CC1PiProject",
					"targetIndexes" : 
					[
						0
					]
				}
			],
			"targets" : 
			[
				{
					"directoryIndex" : 0,
					"id" : "CC1PiProject::@6890427a1f51a3e7e1df",
					"jsonFile" : "target-CC1PiProject-Debug-5053b659b16c65347e5c.json",
					"name" : "CC1PiProject",
					"projectIndex" : 0
				}
			]
		}
	],
	"kind" : "codemodel",
	"paths" : 
	{
		"build" : "/Users/luispelegrinagutierrez/Desktop/Doctorado/Neutrino_Physics_Analisis/CC1PiProject/cmake-build-debug",
		"source" : "/Users/luispelegrinagutierrez/Desktop/Doctorado/Neutrino_Physics_Analisis/CC1PiProject"
	},
	"version" : 
	{
		"major" : 2,
		"minor" : 6
	}
}
